astronomix/__init__.py
astronomix/_finite_difference/_fluid_equations/_eigen.py
astronomix/_finite_difference/_fluid_equations/_enforce_positivity.py
astronomix/_finite_difference/_fluid_equations/_equations.py
astronomix/_finite_difference/_fluid_equations/_fluxes.py
astronomix/_finite_difference/_interface_fluxes/_weno.py
astronomix/_finite_difference/_magnetic_update/_constrained_transport.py
astronomix/_finite_difference/_maths/_differencing.py
astronomix/_finite_difference/_maths/_interpolate.py
astronomix/_finite_difference/_state_evolution/_evolve_state.py
astronomix/_finite_difference/_time_integrators/_ssprk.py
astronomix/_finite_difference/_timestep_estimation/_timestep_estimator.py
astronomix/_finite_volume/_magnetic_update/_magnetic_field_update.py
astronomix/_finite_volume/_magnetic_update/_vector_maths.py
astronomix/_finite_volume/_riemann_solver/__init__.py
astronomix/_finite_volume/_riemann_solver/_lax_friedrichs.py
astronomix/_finite_volume/_riemann_solver/_riemann_solver.py
astronomix/_finite_volume/_riemann_solver/hll.py
astronomix/_finite_volume/_state_evolution/__init__.py
astronomix/_finite_volume/_state_evolution/evolve_state.py
astronomix/_finite_volume/_state_evolution/limited_gradients.py
astronomix/_finite_volume/_state_evolution/limiters.py
astronomix/_finite_volume/_state_evolution/reconstruction.py
astronomix/_finite_volume/_timestep_estimation/_timestep_estimator.py
astronomix/_fluid_equations/__init__.py
astronomix/_fluid_equations/_equations.py
astronomix/_fluid_equations/_fluxes.py
astronomix/_fluid_equations/total_quantities.py
astronomix/_geometry/__init__.py
astronomix/_geometry/boundaries.py
astronomix/_geometry/geometric_terms.py
astronomix/_geometry/geometry.py
astronomix/_physics_modules/__init__.py
astronomix/_physics_modules/_cnn_mhd_corrector/_cnn_mhd_corrector.py
astronomix/_physics_modules/_cnn_mhd_corrector/_cnn_mhd_corrector_options.py
astronomix/_physics_modules/_cooling/_cooling.py
astronomix-0.5.1.dist-info/METADATA
astronomix-0.5.1.dist-info/WHEEL
astronomix-0.5.1.dist-info/licenses/LICENSE
astronomix-0.5.1.dist-info/RECORD
